sniffles/__init__.py
sniffles/cluster.py
sniffles/config.py
sniffles/consensus.py
sniffles/genotyping.py
sniffles/leadprov.py
sniffles/parallel.py
sniffles/postprocessing.py
sniffles/region.py
sniffles/result.py
sniffles/snf.py
sniffles/snfp.py
sniffles/sv.py
sniffles/util.py
sniffles/vcf.py
sniffles/utils/__init__.py
sniffles/utils/resmon.py
sniffles/utils/term_colors.py
sniffles-2.7.2.data/scripts/sniffles
sniffles-2.7.2.dist-info/licenses/LICENSE
sniffles-2.7.2.dist-info/METADATA
sniffles-2.7.2.dist-info/WHEEL
sniffles-2.7.2.dist-info/top_level.txt
sniffles-2.7.2.dist-info/RECORD
