Metadata-Version: 2.4
Name: sniffles
Version: 2.7.2
Summary: A fast structural variation caller for long-read sequencing data
Home-page: https://github.com/fritzsedlazeck/Sniffles
Author: Moritz Smolka, Hermann Romanek
Author-email: moritz.g.smolka@gmail.com, sniffles@romanek.at
License: MIT
Project-URL: Bug Tracker, https://github.com/fritzsedlazeck/Sniffles/issues
Classifier: Programming Language :: Python :: 3
Classifier: License :: OSI Approved :: MIT License
Classifier: Operating System :: OS Independent
Requires-Python: >=3.10
License-File: LICENSE
Requires-Dist: pysam>=0.21.0
Requires-Dist: edlib>=1.3.9
Requires-Dist: psutil>=5.9.4
Requires-Dist: numpy>=2.2.0
Dynamic: author
Dynamic: author-email
Dynamic: description
Dynamic: description-content-type
Dynamic: home-page
Dynamic: license
Dynamic: license-file
Dynamic: summary
